spadesdk/__init__.py
spadesdk/executor.py
spadesdk/file_processor.py
spadesdk/history_provider.py
spadesdk/user.py
spadesdk-0.4.0.dist-info/licenses/LICENSE.txt
spadesdk-0.4.0.dist-info/METADATA
spadesdk-0.4.0.dist-info/WHEEL
spadesdk-0.4.0.dist-info/top_level.txt
spadesdk-0.4.0.dist-info/RECORD
