Metadata-Version: 2.4
Name: spadesdk
Version: 0.4.0
Summary: Spade SDK
Author-email: Marcin Szymanski <marcin.szymanski@crugroup.com>
License:                     GNU GENERAL PUBLIC LICENSE
Project-URL: Source, https://github.com/crugroup/spadesdk
Requires-Python: >=3.11
License-File: LICENSE.txt
Provides-Extra: pandera
Requires-Dist: pandera[io,pandas]>=0.24.0; extra == "pandera"
Dynamic: license-file
